simplepass/__init__.py
simplepass/__main__.py
simplepass/simple.py
simplepass-1.2.11.dist-info/LICENSE
simplepass-1.2.11.dist-info/METADATA
simplepass-1.2.11.dist-info/WHEEL
simplepass-1.2.11.dist-info/entry_points.txt
simplepass-1.2.11.dist-info/top_level.txt
simplepass-1.2.11.dist-info/RECORD
