Metadata-Version: 2.1
Name: simplepass
Version: 1.2.11
Summary: A simple password manager for the command line.
Home-page: https://github.com/jeffmoger/simplepass
Author: Jeff Moger
Author-email: jeff-simple@moger.com
License: UNKNOWN
Platform: UNKNOWN
Classifier: Programming Language :: Python :: 3.7
Classifier: License :: OSI Approved :: GNU General Public License v3 (GPLv3)
Requires-Dist: pyperclip
Requires-Dist: passlib
Requires-Dist: cryptography
Requires-Dist: PyYAML
